google-2.0.3.data/scripts/google
google-2.0.3.dist-info/DESCRIPTION.rst
google-2.0.3.dist-info/METADATA
google-2.0.3.dist-info/RECORD
google-2.0.3.dist-info/WHEEL
google-2.0.3.dist-info/metadata.json
google-2.0.3.dist-info/top_level.txt
googlesearch/__init__.py
googlesearch/user_agents.txt.gz
